awesome_kreport_charts/__init__.py
awesome_kreport_charts/__main__.py
awesome_kreport_charts/charts/__init__.py
awesome_kreport_charts/charts/chart.py
awesome_kreport_charts/charts/sankey_chart.py
awesome_kreport_charts/charts/sunburst_chart.py
awesome_kreport_charts/charts/treemap_chart.py
awesome_kreport_charts/models/__init__.py
awesome_kreport_charts/models/command.py
awesome_kreport_charts/models/tree.py
awesome_kreport_charts/utils/__init__.py
awesome_kreport_charts/utils/constants.py
awesome_kreport_charts/utils/file_processor.py
awesome_kreport_charts/utils/tree_processor.py
awesome_kreport_charts-1.2.0.dist-info/LICENSE
awesome_kreport_charts-1.2.0.dist-info/METADATA
awesome_kreport_charts-1.2.0.dist-info/WHEEL
awesome_kreport_charts-1.2.0.dist-info/top_level.txt
awesome_kreport_charts-1.2.0.dist-info/RECORD
