Metadata-Version: 2.1
Name: awesome-kreport-charts
Version: 1.2.0
Summary: Create awesome charts for kreports (kraken-style reports)
Home-page: https://github.com/taniagmangolini/awesome_kreport_charts
Author: Tania Girao Mangolini
Author-email: tania.mangolini@gmail.com
License: UNKNOWN
Keywords: kraken,kreport,ccmetagen,kraken-style reports
Platform: UNKNOWN
Requires-Dist: pandas (==1.1.5)
Requires-Dist: plotly (==5.3.1)
